diffpy/__init__.py
diffpy/fourigui/__init__.py
diffpy/fourigui/fourigui.py
diffpy/fourigui/version.py
diffpy.fourigui-0.2.0.dist-info/AUTHORS.rst
diffpy.fourigui-0.2.0.dist-info/LICENSE.rst
diffpy.fourigui-0.2.0.dist-info/METADATA
diffpy.fourigui-0.2.0.dist-info/WHEEL
diffpy.fourigui-0.2.0.dist-info/entry_points.txt
diffpy.fourigui-0.2.0.dist-info/top_level.txt
diffpy.fourigui-0.2.0.dist-info/RECORD
