Metadata-Version: 2.1
Name: diffpy.fourigui
Version: 0.2.0
Summary: Tool for visualizing 3D diffraction and PDF Images.
Author-email: "Simon J.L. Billinge group" <simon.billinge@gmail.com>
Maintainer-email: "Simon J.L. Billinge group" <simon.billinge@gmail.com>
Project-URL: Homepage, https://github.com/diffpy/diffpy.fourigui/
Project-URL: Issues, https://github.com/diffpy/diffpy.fourigui/issues/
Keywords: diffraction,pdf,pair distribution function,gui
Classifier: Development Status :: 5 - Production/Stable
Classifier: Environment :: Console
Classifier: Intended Audience :: Developers
Classifier: Intended Audience :: Science/Research
Classifier: License :: OSI Approved :: BSD License
Classifier: Operating System :: MacOS :: MacOS X
Classifier: Operating System :: Microsoft :: Windows
Classifier: Operating System :: POSIX
Classifier: Operating System :: Unix
Classifier: Programming Language :: Python :: 3.11
Classifier: Programming Language :: Python :: 3.12
Classifier: Programming Language :: Python :: 3.13
Classifier: Topic :: Scientific/Engineering :: Physics
Classifier: Topic :: Scientific/Engineering :: Chemistry
Requires-Python: <3.14,>=3.11
License-File: LICENSE.rst
License-File: AUTHORS.rst
Requires-Dist: h5py
Requires-Dist: tk
Requires-Dist: matplotlib
Requires-Dist: numpy
